snoop/__init__.py
snoop/configuration.py
snoop/formatting.py
snoop/ipython.py
snoop/pp_module.py
snoop/tracer.py
snoop/utils.py
snoop/variables.py
snoop/version.py
snoop-0.6.0.dist-info/LICENSE.txt
snoop-0.6.0.dist-info/METADATA
snoop-0.6.0.dist-info/WHEEL
snoop-0.6.0.dist-info/top_level.txt
snoop-0.6.0.dist-info/RECORD
