Metadata-Version: 2.1
Name: snoop
Version: 0.6.0
Summary: Powerful debugging tools for Python
Home-page: https://github.com/alexmojaki/snoop
Author: Alex Hall
Author-email: alex.mojaki@gmail.com
License: MIT
Classifier: License :: OSI Approved :: MIT License
Classifier: Programming Language :: Python
Classifier: Programming Language :: Python :: 3.8
Classifier: Programming Language :: Python :: 3.9
Classifier: Programming Language :: Python :: 3.10
Classifier: Programming Language :: Python :: 3.11
Classifier: Programming Language :: Python :: 3.12
Classifier: Programming Language :: Python :: 3.13
Classifier: Operating System :: OS Independent
Classifier: Topic :: Software Development :: Debuggers
Classifier: Programming Language :: Python :: Implementation :: CPython
Classifier: Programming Language :: Python :: Implementation :: PyPy
Classifier: Environment :: Console
Requires-Python: >=3.8
License-File: LICENSE.txt
Requires-Dist: cheap_repr>=0.4.0
Requires-Dist: executing
Requires-Dist: asttokens
Requires-Dist: pygments
Provides-Extra: tests
Requires-Dist: pytest; extra == "tests"
Requires-Dist: littleutils; extra == "tests"
Requires-Dist: prettyprinter; extra == "tests"
Requires-Dist: pprintpp; extra == "tests"
Requires-Dist: pytest-order; extra == "tests"
Requires-Dist: pandas>=0.24.2; platform_python_implementation != "PyPy" and extra == "tests"
Requires-Dist: numpy>=1.16.5; platform_python_implementation != "PyPy" and extra == "tests"
Requires-Dist: birdseye; platform_python_implementation != "PyPy" and extra == "tests"
Requires-Dist: Django; extra == "tests"
